os2ds_rules-0.1.0.dist-info/METADATA
os2ds_rules-0.1.0.dist-info/LICENSE
os2ds_rules-0.1.0.dist-info/WHEEL
os2ds_rules-0.1.0.dist-info/RECORD
os2ds_rules-0.1.0.dist-info/top_level.txt
os2ds_rules/address_rule.cpp
os2ds_rules/wordlist_rule.cpython-39-x86_64-linux-gnu.so
os2ds_rules/name_rule.cpp
os2ds_rules/cpr_detector.cpython-39-x86_64-linux-gnu.so
os2ds_rules/cpr.cpp
os2ds_rules/name_rule.cpython-39-x86_64-linux-gnu.so
os2ds_rules/wordlist_rule.cpp
os2ds_rules/__init__.py
os2ds_rules/address_rule.cpython-39-x86_64-linux-gnu.so
