Metadata-Version: 2.1
Name: os2ds-rules
Version: 0.1.0
Summary: Text processing tool for detecting Danish CPR-numbers.
Author-email: HackTheOxidation <tomas.hagenau@protonmail.ch>
License: Mozilla Public License Version 2.0
Project-URL: Homepage, https://codeberg.org/HackTheOxidation/cpr-detector
Project-URL: Bug Tracker, https://codeberg.org/HackTheOxidation/cpr-detector/issues
Classifier: Programming Language :: Python :: 3
Requires-Python: >=3.9
License-File: LICENSE
